LICENSE.txt
MANIFEST.in
README.rst
setup.py
doc/man/man1/Makefile
doc/man/man1/sas_counters.1
doc/man/man1/sas_devices.1
doc/man/man1/sas_discover.1
doc/man/man1/ses_report.1
doc/txt/sas_counters.txt
doc/txt/sas_devices.txt
doc/txt/sas_discover.txt
doc/txt/ses_report.txt
sasutils/__init__.py
sasutils/sas.py
sasutils/scsi.py
sasutils/ses.py
sasutils/smp.py
sasutils/sysfs.py
sasutils/vpd.py
sasutils.egg-info/PKG-INFO
sasutils.egg-info/SOURCES.txt
sasutils.egg-info/dependency_links.txt
sasutils.egg-info/entry_points.txt
sasutils.egg-info/top_level.txt
sasutils/cli/__init__.py
sasutils/cli/sas_counters.py
sasutils/cli/sas_devices.py
sasutils/cli/sas_discover.py
sasutils/cli/sas_mpath_snic_alias.py
sasutils/cli/sas_sd_snic_alias.py
sasutils/cli/sas_st_snic_alias.py
sasutils/cli/ses_report.py