Metadata-Version: 1.1
Name: sasutils
Version: 0.6.0
Summary: Serial Attached SCSI (SAS) Linux utilities
Home-page: https://github.com/stanford-rc/sasutils
Author: Stephane Thiell
Author-email: sthiell@stanford.edu
License: Apache Software License
Keywords: SAS,SCSI,storage
Platform: GNU/Linux
Classifier: Development Status :: 5 - Production/Stable
Classifier: Environment :: Console
Classifier: Intended Audience :: System Administrators
Classifier: License :: OSI Approved :: Apache Software License
Classifier: Operating System :: POSIX :: Linux
Classifier: Programming Language :: Python
Classifier: Programming Language :: Python :: 3
Classifier: Topic :: System :: Systems Administration
License-File: LICENSE.txt
